{
  "stellarity:cursed_tome/root": {
    "criteria": {
      "requirement": "2024-03-16 19:55:18 +0000"
    },
    "done": true
  },
  "minecraft:recipes/decorations/crafting_table": {
    "criteria": {
      "unlock_right_away": "2024-03-16 19:55:18 +0000"
    },
    "done": true
  },
  "iceandfire:iceandfire/root": {
    "criteria": {
      "tick": "2024-03-16 19:55:18 +0000"
    },
    "done": true
  },
  "stellarity:dragons_den/cursed_tome/root": {
    "criteria": {
      "requirement": "2024-03-16 19:55:18 +0000"
    },
    "done": true
  },
  "grimoireofgaia:main/root": {
    "criteria": {
      "join": "2024-03-16 19:55:18 +0000"
    },
    "done": true
  },
  "tombstone:adventure/root": {
    "criteria": {
      "auto": "2024-03-16 19:55:18 +0000"
    },
    "done": true
  },
  "regions_unexplored:parent": {
    "criteria": {
      "load_in_world": "2024-03-16 19:55:18 +0000"
    },
    "done": true
  },
  "cataclysm:root": {
    "criteria": {
      "custom_test_name": "2024-03-16 19:55:18 +0000"
    },
    "done": true
  },
  "regions_unexplored:regions_explored": {
    "criteria": {
      "sparse_redwoods": "2024-03-16 19:55:18 +0000"
    },
    "done": false
  },
  "farmersdelight:main/root": {
    "criteria": {
      "seeds": "2024-03-16 19:55:18 +0000"
    },
    "done": true
  },
  "regions_unexplored:pioneer": {
    "criteria": {
      "sparse_redwoods": "2024-03-16 19:55:18 +0000"
    },
    "done": false
  },
  "DataVersion": 3465
}